jsonfield/__init__.py
jsonfield/encoder.py
jsonfield/fields.py
jsonfield/forms.py
jsonfield/json.py
jsonfield2-4.0.0.post0.dist-info/LICENSE
jsonfield2-4.0.0.post0.dist-info/METADATA
jsonfield2-4.0.0.post0.dist-info/WHEEL
jsonfield2-4.0.0.post0.dist-info/top_level.txt
jsonfield2-4.0.0.post0.dist-info/RECORD
