Metadata-Version: 1.1
Name: jsonfield2
Version: 4.0.0.post0
Summary: A reusable Django field that allows you to store validated JSON in your model.
Home-page: https://github.com/rpkilby/jsonfield2/
Author: Ryan P Kilby
Author-email: rpkilby@ncsu.edu
License: MIT
Platform: UNKNOWN
Classifier: Environment :: Web Environment
Classifier: Framework :: Django
Classifier: Framework :: Django :: 2.2
Classifier: Framework :: Django :: 3.0
Classifier: Intended Audience :: Developers
Classifier: Operating System :: OS Independent
Classifier: Programming Language :: Python
Classifier: Programming Language :: Python :: 3
Classifier: Programming Language :: Python :: 3.6
Classifier: Programming Language :: Python :: 3.7
Classifier: Programming Language :: Python :: 3.8
Classifier: Framework :: Django
